bilibili/server.py
bilibili_mcp_server-0.1.0.dist-info/METADATA
bilibili_mcp_server-0.1.0.dist-info/WHEEL
bilibili_mcp_server-0.1.0.dist-info/entry_points.txt
bilibili_mcp_server-0.1.0.dist-info/top_level.txt
bilibili_mcp_server-0.1.0.dist-info/RECORD
